{
  "id": "6d065e1c-f823-492c-bd1e-ccd8a197a27d",
  "prevId": "00000000-0000-0000-0000-000000000000",
  "version": "7",
  "dialect": "postgresql",
  "tables": {
    "public.employee": {
      "name": "employee",
      "schema": "",
      "columns": {
        "id": {
          "name": "id",
          "type": "serial",
          "primaryKey": true,
          "notNull": true
        },
        "full_name": {
          "name": "full_name",
          "type": "varchar(128)",
          "primaryKey": false,
          "notNull": true
        },
        "first_name": {
          "name": "first_name",
          "type": "varchar(128)",
          "primaryKey": false,
          "notNull": true
        },
        "last_name": {
          "name": "last_name",
          "type": "varchar(128)",
          "primaryKey": false,
          "notNull": true
        },
        "group_id": {
          "name": "group_id",
          "type": "integer",
          "primaryKey": false,
          "notNull": false
        }
      },
      "indexes": {},
      "foreignKeys": {
        "employee_group_id_group_id_fk": {
          "name": "employee_group_id_group_id_fk",
          "tableFrom": "employee",
          "tableTo": "group",
          "columnsFrom": [
            "group_id"
          ],
          "columnsTo": [
            "id"
          ],
          "onDelete": "no action",
          "onUpdate": "no action"
        }
      },
      "compositePrimaryKeys": {},
      "uniqueConstraints": {
        "employee_full_name_unique": {
          "name": "employee_full_name_unique",
          "nullsNotDistinct": false,
          "columns": [
            "full_name"
          ]
        }
      }
    },
    "public.group": {
      "name": "group",
      "schema": "",
      "columns": {
        "id": {
          "name": "id",
          "type": "serial",
          "primaryKey": true,
          "notNull": true
        },
        "name": {
          "name": "name",
          "type": "varchar(128)",
          "primaryKey": false,
          "notNull": true
        },
        "default_group": {
          "name": "default_group",
          "type": "boolean",
          "primaryKey": false,
          "notNull": true,
          "default": false
        }
      },
      "indexes": {},
      "foreignKeys": {},
      "compositePrimaryKeys": {},
      "uniqueConstraints": {
        "group_name_unique": {
          "name": "group_name_unique",
          "nullsNotDistinct": false,
          "columns": [
            "name"
          ]
        }
      }
    },
    "public.schedule": {
      "name": "schedule",
      "schema": "",
      "columns": {
        "id": {
          "name": "id",
          "type": "serial",
          "primaryKey": true,
          "notNull": true
        },
        "employee_id": {
          "name": "employee_id",
          "type": "integer",
          "primaryKey": false,
          "notNull": true
        },
        "shift_id": {
          "name": "shift_id",
          "type": "integer",
          "primaryKey": false,
          "notNull": true
        },
        "year": {
          "name": "year",
          "type": "integer",
          "primaryKey": false,
          "notNull": true
        },
        "month": {
          "name": "month",
          "type": "integer",
          "primaryKey": false,
          "notNull": true
        },
        "day": {
          "name": "day",
          "type": "integer",
          "primaryKey": false,
          "notNull": true
        }
      },
      "indexes": {},
      "foreignKeys": {
        "schedule_employee_id_employee_id_fk": {
          "name": "schedule_employee_id_employee_id_fk",
          "tableFrom": "schedule",
          "tableTo": "employee",
          "columnsFrom": [
            "employee_id"
          ],
          "columnsTo": [
            "id"
          ],
          "onDelete": "no action",
          "onUpdate": "no action"
        },
        "schedule_shift_id_shift_id_fk": {
          "name": "schedule_shift_id_shift_id_fk",
          "tableFrom": "schedule",
          "tableTo": "shift",
          "columnsFrom": [
            "shift_id"
          ],
          "columnsTo": [
            "id"
          ],
          "onDelete": "no action",
          "onUpdate": "no action"
        }
      },
      "compositePrimaryKeys": {},
      "uniqueConstraints": {}
    },
    "public.shift": {
      "name": "shift",
      "schema": "",
      "columns": {
        "id": {
          "name": "id",
          "type": "serial",
          "primaryKey": true,
          "notNull": true
        },
        "comment": {
          "name": "comment",
          "type": "varchar(128)",
          "primaryKey": false,
          "notNull": false
        },
        "start": {
          "name": "start",
          "type": "time",
          "primaryKey": false,
          "notNull": true
        },
        "end": {
          "name": "end",
          "type": "time",
          "primaryKey": false,
          "notNull": true
        },
        "color": {
          "name": "color",
          "type": "varchar",
          "primaryKey": false,
          "notNull": false
        }
      },
      "indexes": {},
      "foreignKeys": {},
      "compositePrimaryKeys": {},
      "uniqueConstraints": {}
    }
  },
  "enums": {},
  "schemas": {},
  "sequences": {},
  "_meta": {
    "columns": {},
    "schemas": {},
    "tables": {}
  }
}